P3/nivel 1/nivel 2/Decodificador driver de 7 segmentos/decodificador_de_7_seg.v
module decodificador_de_7_seg (input wire [3:0] sec_ones, sec_tens, mins,
                                    output wire [6:0] sec_ones_segs, sec_tens_segs, mins_segs);


    assign sec_ones_segs = 
    /* 0 */ (sec_ones == 4'b0000) ? 7'b000_0001 : 
    /* 1 */ (sec_ones == 4'b0001) ? 7'b100_1111 :
    /* 2 */ (sec_ones == 4'b0010) ? 7'b001_0010 :
    /* 3 */ (sec_ones == 4'b0011) ? 7'b000_0110 :
    /* 4 */ (sec_ones == 4'b0100) ? 7'b100_1100 :
    /* 5 */ (sec_ones == 4'b0101) ? 7'b010_0100 :
    /* 6 */ (sec_ones == 4'b0110) ? 7'b010_0000 :
    /* 7 */ (sec_ones == 4'b0111) ? 7'b000_1111 :
    /* 8 */ (sec_ones == 4'b1000) ? 7'b000_0000 :
    /* 9 */ (sec_ones == 4'b1001) ? 7'b000_0100 :
    /* d */ 8'bXXXX_XXXX;

        assign sec_tens_segs = 
    /* 0 */ (sec_tens == 4'b0000) ? 7'b000_0001 : 
    /* 1 */ (sec_tens == 4'b0001) ? 7'b100_1111 :
    /* 2 */ (sec_tens == 4'b0010) ? 7'b001_0010 :
    /* 3 */ (sec_tens == 4'b0011) ? 7'b000_0110 :
    /* 4 */ (sec_tens == 4'b0100) ? 7'b100_1100 :
    /* 5 */ (sec_tens == 4'b0101) ? 7'b010_0100 :
    /* 6 */ (sec_tens == 4'b0110) ? 7'b010_0000 :
    /* 7 */ (sec_tens == 4'b0111) ? 7'b000_1111 :
    /* 8 */ (sec_tens == 4'b1000) ? 7'b000_0000 :
    /* 9 */ (sec_tens == 4'b1001) ? 7'b000_0100 :
    /* d */ 8'bXXXX_XXXX;

    assign mins_segs = 
    /* 0 */ (mins == 4'b0000) ? 7'b000_0001 : 
    /* 1 */ (mins == 4'b0001) ? 7'b100_1111 :
    /* 2 */ (mins == 4'b0010) ? 7'b001_0010 :
    /* 3 */ (mins == 4'b0011) ? 7'b000_0110 :
    /* 4 */ (mins == 4'b0100) ? 7'b100_1100 :
    /* 5 */ (mins == 4'b0101) ? 7'b010_0100 :
    /* 6 */ (mins == 4'b0110) ? 7'b010_0000 :
    /* 7 */ (mins == 4'b0111) ? 7'b000_1111 :
    /* 8 */ (mins == 4'b1000) ? 7'b000_0000 :
    /* 9 */ (mins == 4'b1001) ? 7'b000_0100 :
    /* d */ 8'bXXXX_XXXX;

    
endmodule

P3/nivel 1/nivel 2/Decodificador driver de 7 segmentos/decodificador_de_7_seg_tb.v
`timescale 1ps/1ps
`include "decodificador_de_7_seg.v"

module decodificador_de_7_seg_tb();

    reg[3:0] sec_ones, sec_tens, mins;
    wire[6:0] sec_ones_segs, sec_tens_segs, mins_segs;

    decodificador_de_7_seg DUT(.sec_ones(sec_ones), .sec_tens(sec_tens), .mins(mins),
                                .sec_ones_segs(sec_ones_segs), .sec_tens_segs(sec_tens_segs), .mins_segs(mins_segs));

    initial begin
        $dumpfile("decodificador_de_7_seg_tb.vcd");
        $dumpvars(0, decodificador_de_7_seg_tb);

    /* 0 */ sec_ones = 4'b0000; sec_tens = 4'b0000; mins = 4'b0000;
    #5
    /* 1 */ sec_ones = 4'b0001; sec_tens = 4'b0001; mins = 4'b0001;
    #5
    /* 2 */ sec_ones = 4'b0010; sec_tens = 4'b0010; mins = 4'b0010;
    #5
    /* 3 */ sec_ones = 4'b0011; sec_tens = 4'b0011; mins = 4'b0011;
    #5
    /* 4 */ sec_ones = 4'b0100; sec_tens = 4'b0100; mins = 4'b0100;
    #5
    /* 5 */ sec_ones = 4'b0101; sec_tens = 4'b0101; mins = 4'b0101;
    #5
    /* 6 */ sec_ones = 4'b0110; sec_tens = 4'b0110; mins = 4'b0110;
    #5
    /* 7 */ sec_ones = 4'b0111; sec_tens = 4'b0111; mins = 4'b0111;
    #5
    /* 8 */ sec_ones = 4'b1000; sec_tens = 4'b1000; mins = 4'b1000;
    #5
    /* 9 */ sec_ones = 4'b1001; sec_tens = 4'b1001; mins = 4'b1001;


    


    end



endmodule

P3/nivel 1/nivel 2/Decodificador driver de 7 segmentos/decodificador_de_7_seg_tb.vcd
$date
	Sat Sep 23 18:58:55 2023
$end
$version
	Icarus Verilog
$end
$timescale
	1ps
$end
$scope module decodificador_de_7_seg_tb $end
$var wire 7 ! sec_tens_segs [6:0] $end
$var wire 7 " sec_ones_segs [6:0] $end
$var wire 7 # mins_segs [6:0] $end
$var reg 4 $ mins [3:0] $end
$var reg 4 % sec_ones [3:0] $end
$var reg 4 & sec_tens [3:0] $end
$scope module DUT $end
$var wire 4 ' mins [3:0] $end
$var wire 4 ( sec_ones [3:0] $end
$var wire 4 ) sec_tens [3:0] $end
$var wire 7 * sec_tens_segs [6:0] $end
$var wire 7 + sec_ones_segs [6:0] $end
$var wire 7 , mins_segs [6:0] $end
$upscope $end
$upscope $end
$enddefinitions $end
$comment Show the parameter values. $end
$dumpall
$end
#0
$dumpvars
b1 ,
b1 +
b1 *
b0 )
b0 (
b0 '
b0 &
b0 %
b0 $
b1 #
b1 "
b1 !
$end
#5
b1001111 #
b1001111 ,
b1001111 !
b1001111 *
b1001111 "
b1001111 +
b1 $
b1 '
b1 &
b1 )
b1 %
b1 (
#10
b10010 #
b10010 ,
b10010 !
b10010 *
b10010 "
b10010 +
b10 $
b10 '
b10 &
b10 )
b10 %
b10 (
#15
b110 #
b110 ,
b110 !
b110 *
b110 "
b110 +
b11 $
b11 '
b11 &
b11 )
b11 %
b11 (
#20
b1001100 #
b1001100 ,
b1001100 !
b1001100 *
b1001100 "
b1001100 +
b100 $
b100 '
b100 &
b100 )
b100 %
b100 (
#25
b100100 #
b100100 ,
b100100 !
b100100 *
b100100 "
b100100 +
b101 $
b101 '
b101 &
b101 )
b101 %
b101 (
#30
b100000 #
b100000 ,
b100000 !
b100000 *
b100000 "
b100000 +
b110 $
b110 '
b110 &
b110 )
b110 %
b110 (
#35
b1111 #
b1111 ,
b1111 !
b1111 *
b1111 "
b1111 +
b111 $
b111 '
b111 &
b111 )
b111 %
b111 (
#40
b0 #
b0 ,
b0 !
b0 *
b0 "
b0 +
b1000 $
b1000 '
b1000 &
b1000 )
b1000 %
b1000 (
#45
b100 #
b100 ,
b100 !
b100 *
b100 "
b100 +
b1001 $
b1001 '
b1001 &
b1001 )
b1001 %
b1001 (
