P3/nivel 1/nivel 2/Timer de minutos segundos/nivel 3/Contador MOD10/Contador MOD10.v
module Contador_mod10 (input wire loadn, clrn, clock, enable, input wire [3:0] data,
                        output wire tc, zero, output reg [3:0] ones);


    always@(negedge clrn)begin
        if(clrn == 0)
            ones = 0;
    end

    assign zero = (ones == 0)? 1:0;
    assign tc = enable && zero;

    always@(posedge clock) begin
        if(enable == 1)
            if(ones == 0)
                ones <= 9;
            else
                ones <= ones -1;
        else
            begin
                if(loadn == 0)
                    ones <= data;
            end
    end

endmodule

P3/nivel 1/nivel 2/Timer de minutos segundos/nivel 3/Contador MOD6/Contador MOD6.v
module Contador_mod6 (input wire loadn, clrn, clock, enable, input wire [3:0] data,
                        output wire tc, zero, output reg [3:0] tens);


    always@(negedge clrn)begin
        if(clrn == 0)
            tens = 0;
    end

    assign zero = (tens == 0)? 1:0;
    assign tc = enable && zero;

    always@(posedge clock) begin
        if(enable == 1)
            if(tens == 0)
                tens <= 5;
            else
                tens <= tens -1;
        else
            begin
                if(loadn == 0)
                    tens <= data;
            end
    end

endmodule

P3/nivel 1/nivel 2/Timer de minutos segundos/Timer de minutos segundos.v
`include "nivel 3\\Contador MOD6\\Contador MOD6.v"
`include "nivel 3\\Contador MOD10\\Contador MOD10.v"

module Controlador_timer (input wire  loadn, clrn, clock, en, input wire[3:0] data,
                          output wire zero, output wire [3:0] sec_ones, sec_tens, mins);
    
    wire zero1, zero2, zero3;
    wire tc1, tc2, tc3;
    Contador_mod10 DUT1(.loadn(loadn), .clrn(clrn), .clock(clock), .enable(en), .data(data), .tc(tc1), .zero(zero1), .ones(sec_ones));
    Contador_mod6 DUT2(.loadn(loadn), .clrn(clrn), .clock(clock), .enable(tc1), .data(sec_ones), .tens(sec_tens), .tc(tc2), .zero(zero2));
    Contador_mod10 DUT3(.loadn(loadn), .clrn(clrn), .clock(clock), .enable(tc2), .data(sec_tens), .tc(tc3), .zero(zero3), .ones(mins));
    assign zero = zero1 && zero2 && zero3;

endmodule

P3/nivel 1/nivel 2/Timer de minutos segundos/Controlador_timer_tb.v
`timescale 1ps/1ps
`include "Timer de minutos segundos.v"

module Controlador_timer_tb();

    reg loadn, clrn, clock, en; 
    reg[3:0] data;
    wire zero;
    wire [3:0] sec_ones, sec_tens, mins;


    Controlador_timer DUT(.loadn(loadn), .clrn(clrn), .clock(clock), .en(en), .data(data),
                            .zero(zero), .sec_ones(sec_ones), .sec_tens(sec_tens), .mins(mins));


    initial begin
        $dumpfile("Controlador_timer_tb.vcd");
        $dumpvars(0, Controlador_timer_tb);
        clock  = 1'b0;
        en = 1'b0; 
        loadn  = 1'b0;
    end

    always begin
        #1 clock = loadn? ~clock : clock;
    end

    initial begin    

        clrn = 1'b1; #0.5
        clrn = 1'b0; #0.5
        clrn = 1'b1; #0.5

        data =  2;   #0.04;
        clock = 1'b1;   #0.01;
        clock = 1'b0;   #0.95;

        data =  1;   #0.04;
        clock = 1'b1;   #0.01;
        clock = 1'b0;   #0.95;

        data =  5;   #0.04;
        clock = 1'b1;   #0.01;
        clock = 1'b0;   #0.95;

        data =  9;   #0.04;
        clock= 1'b1;   #0.01;
        clock = 1'b0;   #0.95;

        en = 1; loadn = 1; #1000;

        $finish();
    end


endmodule

P3/nivel 1/nivel 2/Timer de minutos segundos/Controlador_timer_tb.vcd
$date
	Sat Sep 23 22:12:15 2023
$end
$version
	Icarus Verilog
$end
$timescale
	1ps
$end
$scope module Controlador_timer_tb $end
$var wire 1 ! zero $end
$var wire 4 " sec_tens [3:0] $end
$var wire 4 # sec_ones [3:0] $end
$var wire 4 $ mins [3:0] $end
$var reg 1 % clock $end
$var reg 1 & clrn $end
$var reg 4 ' data [3:0] $end
$var reg 1 ( en $end
$var reg 1 ) loadn $end
$scope module DUT $end
$var wire 1 % clock $end
$var wire 1 & clrn $end
$var wire 4 * data [3:0] $end
$var wire 1 ( en $end
$var wire 1 ) loadn $end
$var wire 1 ! zero $end
$var wire 1 + zero3 $end
$var wire 1 , zero2 $end
$var wire 1 - zero1 $end
$var wire 1 . tc3 $end
$var wire 1 / tc2 $end
$var wire 1 0 tc1 $end
$var wire 4 1 sec_tens [3:0] $end
$var wire 4 2 sec_ones [3:0] $end
$var wire 4 3 mins [3:0] $end
$scope module DUT1 $end
$var wire 1 % clock $end
$var wire 1 & clrn $end
$var wire 4 4 data [3:0] $end
$var wire 1 ( enable $end
$var wire 1 ) loadn $end
$var wire 1 0 tc $end
$var wire 1 - zero $end
$var reg 4 5 ones [3:0] $end
$upscope $end
$scope module DUT2 $end
$var wire 1 % clock $end
$var wire 1 & clrn $end
$var wire 4 6 data [3:0] $end
$var wire 1 0 enable $end
$var wire 1 ) loadn $end
$var wire 1 / tc $end
$var wire 1 , zero $end
$var reg 4 7 tens [3:0] $end
$upscope $end
$scope module DUT3 $end
$var wire 1 % clock $end
$var wire 1 & clrn $end
$var wire 4 8 data [3:0] $end
$var wire 1 / enable $end
$var wire 1 ) loadn $end
$var wire 1 . tc $end
$var wire 1 + zero $end
$var reg 4 9 ones [3:0] $end
$upscope $end
$upscope $end
$upscope $end
$enddefinitions $end
$comment Show the parameter values. $end
$dumpall
$end
#0
$dumpvars
bx 9
bx 8
bx 7
bx 6
bx 5
bx 4
bx 3
bx 2
bx 1
00
0/
0.
x-
x,
x+
bx *
0)
0(
bx '
1&
0%
bx $
bx #
bx "
x!
$end
#1
1!
1-
1,
1+
b0 #
b0 2
b0 5
b0 6
b0 "
b0 1
b0 7
b0 8
b0 $
b0 3
b0 9
0&
#2
1&
#3
0!
0-
b10 #
b10 2
b10 5
b10 6
0%
b10 '
b10 *
b10 4
#4
0,
b10 "
b10 1
b10 7
b10 8
b1 #
b1 2
b1 5
b1 6
0%
b1 '
b1 *
b1 4
#5
0+
b101 #
b101 2
b101 5
b101 6
b1 "
b1 1
b1 7
b1 8
b10 $
b10 3
b10 9
0%
b101 '
b101 *
b101 4
#6
b1 $
b1 3
b1 9
b101 "
b101 1
b101 7
b101 8
b1001 #
b1001 2
b1001 5
b1001 6
0%
b1001 '
b1001 *
b1001 4
#7
1)
1(
#8
b1000 #
b1000 2
b1000 5
b1000 6
1%
#9
0%
#10
b111 #
b111 2
b111 5
b111 6
1%
#11
0%
#12
b110 #
b110 2
b110 5
b110 6
1%
#13
0%
#14
b101 #
b101 2
b101 5
b101 6
1%
#15
0%
#16
b100 #
b100 2
b100 5
b100 6
1%
#17
0%
#18
b11 #
b11 2
b11 5
b11 6
1%
#19
0%
#20
b10 #
b10 2
b10 5
b10 6
1%
#21
0%
#22
b1 #
b1 2
b1 5
b1 6
1%
#23
0%
#24
10
1-
b0 #
b0 2
b0 5
b0 6
1%
#25
0%
#26
00
0-
b100 "
b100 1
b100 7
b100 8
b1001 #
b1001 2
b1001 5
b1001 6
1%
#27
0%
#28
b1000 #
b1000 2
b1000 5
b1000 6
1%
#29
0%
#30
b111 #
b111 2
b111 5
b111 6
1%
#31
0%
#32
b110 #
b110 2
b110 5
b110 6
1%
#33
0%
#34
b101 #
b101 2
b101 5
b101 6
1%
#35
0%
#36
b100 #
b100 2
b100 5
b100 6
1%
#37
0%
#38
b11 #
b11 2
b11 5
b11 6
1%
#39
0%
#40
b10 #
b10 2
b10 5
b10 6
1%
#41
0%
#42
b1 #
b1 2
b1 5
b1 6
1%
#43
0%
#44
10
1-
b0 #
b0 2
b0 5
b0 6
1%
#45
0%
#46
00
0-
b11 "
b11 1
b11 7
b11 8
b1001 #
b1001 2
b1001 5
b1001 6
1%
#47
0%
#48
b1000 #
b1000 2
b1000 5
b1000 6
1%
#49
0%
#50
b111 #
b111 2
b111 5
b111 6
1%
#51
0%
#52
b110 #
b110 2
b110 5
b110 6
1%
#53
0%
#54
b101 #
b101 2
b101 5
b101 6
1%
#55
0%
#56
b100 #
b100 2
b100 5
b100 6
1%
#57
0%
#58
b11 #
b11 2
b11 5
b11 6
1%
#59
0%
#60
b10 #
b10 2
b10 5
b10 6
1%
#61
0%
#62
b1 #
b1 2
b1 5
b1 6
1%
#63
0%
#64
10
1-
b0 #
b0 2
b0 5
b0 6
1%
#65
0%
#66
00
0-
b10 "
b10 1
b10 7
b10 8
b1001 #
b1001 2
b1001 5
b1001 6
1%
#67
0%
#68
b1000 #
b1000 2
b1000 5
b1000 6
1%
#69
0%
#70
b111 #
b111 2
b111 5
b111 6
1%
#71
0%
#72
b110 #
b110 2
b110 5
b110 6
1%
#73
0%
#74
b101 #
b101 2
b101 5
b101 6
1%
#75
0%
#76
b100 #
b100 2
b100 5
b100 6
1%
#77
0%
#78
b11 #
b11 2
b11 5
b11 6
1%
#79
0%
#80
b10 #
b10 2
b10 5
b10 6
1%
#81
0%
#82
b1 #
b1 2
b1 5
b1 6
1%
#83
0%
#84
10
1-
b0 #
b0 2
b0 5
b0 6
1%
#85
0%
#86
00
0-
b1 "
b1 1
b1 7
b1 8
b1001 #
b1001 2
b1001 5
b1001 6
1%
#87
0%
#88
b1000 #
b1000 2
b1000 5
b1000 6
1%
#89
0%
#90
b111 #
b111 2
b111 5
b111 6
1%
#91
0%
#92
b110 #
b110 2
b110 5
b110 6
1%
#93
0%
#94
b101 #
b101 2
b101 5
b101 6
1%
#95
0%
#96
b100 #
b100 2
b100 5
b100 6
1%
#97
0%
#98
b11 #
b11 2
b11 5
b11 6
1%
#99
0%
#100
b10 #
b10 2
b10 5
b10 6
1%
#101
0%
#102
b1 #
b1 2
b1 5
b1 6
1%
#103
0%
#104
10
1-
b0 #
b0 2
b0 5
b0 6
1%
#105
0%
#106
00
1,
0-
b0 "
b0 1
b0 7
b0 8
b1001 #
b1001 2
b1001 5
b1001 6
1%
#107
0%
#108
b1000 #
b1000 2
b1000 5
b1000 6
1%
#109
0%
#110
b111 #
b111 2
b111 5
b111 6
1%
#111
0%
#112
b110 #
b110 2
b110 5
b110 6
1%
#113
0%
#114
b101 #
b101 2
b101 5
b101 6
1%
#115
0%
#116
b100 #
b100 2
b100 5
b100 6
1%
#117
0%
#118
b11 #
b11 2
b11 5
b11 6
1%
#119
0%
#120
b10 #
b10 2
b10 5
b10 6
1%
#121
0%
#122
b1 #
b1 2
b1 5
b1 6
1%
#123
0%
#124
1/
10
1-
b0 #
b0 2
b0 5
b0 6
1%
#125
0%
#126
0/
00
1+
0,
0-
b0 $
b0 3
b0 9
b101 "
b101 1
b101 7
b101 8
b1001 #
b1001 2
b1001 5
b1001 6
1%
#127
0%
#128
b1000 #
b1000 2
b1000 5
b1000 6
1%
#129
0%
#130
b111 #
b111 2
b111 5
b111 6
1%
#131
0%
#132
b110 #
b110 2
b110 5
b110 6
1%
#133
0%
#134
b101 #
b101 2
b101 5
b101 6
1%
#135
0%
#136
b100 #
b100 2
b100 5
b100 6
1%
#137
0%
#138
b11 #
b11 2
b11 5
b11 6
1%
#139
0%
#140
b10 #
b10 2
b10 5
b10 6
1%
#141
0%
#142
b1 #
b1 2
b1 5
b1 6
1%
#143
0%
#144
10
1-
b0 #
b0 2
b0 5
b0 6
1%
#145
0%
#146
00
0-
b100 "
b100 1
b100 7
b100 8
b1001 #
b1001 2
b1001 5
b1001 6
1%
#147
0%
#148
b1000 #
b1000 2
b1000 5
b1000 6
1%
#149
0%
#150
b111 #
b111 2
b111 5
b111 6
1%
#151
0%
#152
b110 #
b110 2
b110 5
b110 6
1%
#153
0%
#154
b101 #
b101 2
b101 5
b101 6
1%
#155
0%
#156
b100 #
b100 2
b100 5
b100 6
1%
#157
0%
#158
b11 #
b11 2
b11 5
b11 6
1%
#159
0%
#160
b10 #
b10 2
b10 5
b10 6
1%
#161
0%
#162
b1 #
b1 2
b1 5
b1 6
1%
#163
0%
#164
10
1-
b0 #
b0 2
b0 5
b0 6
1%
#165
0%
#166
00
0-
b11 "
b11 1
b11 7
b11 8
b1001 #
b1001 2
b1001 5
b1001 6
1%
#167
0%
#168
b1000 #
b1000 2
b1000 5
b1000 6
1%
#169
0%
#170
b111 #
b111 2
b111 5
b111 6
1%
#171
0%
#172
b110 #
b110 2
b110 5
b110 6
1%
#173
0%
#174
b101 #
b101 2
b101 5
b101 6
1%
#175
0%
#176
b100 #
b100 2
b100 5
b100 6
1%
#177
0%
#178
b11 #
b11 2
b11 5
b11 6
1%
#179
0%
#180
b10 #
b10 2
b10 5
b10 6
1%
#181
0%
#182
b1 #
b1 2
b1 5
b1 6
1%
#183
0%
#184
10
1-
b0 #
b0 2
b0 5
b0 6
1%
#185
0%
#186
00
0-
b10 "
b10 1
b10 7
b10 8
b1001 #
b1001 2
b1001 5
b1001 6
1%
#187
0%
#188
b1000 #
b1000 2
b1000 5
b1000 6
1%
#189
0%
#190
b111 #
b111 2
b111 5
b111 6
1%
#191
0%
#192
b110 #
b110 2
b110 5
b110 6
1%
#193
0%
#194
b101 #
b101 2
b101 5
b101 6
1%
#195
0%
#196
b100 #
b100 2
b100 5
b100 6
1%
#197
0%
#198
b11 #
b11 2
b11 5
b11 6
1%
#199
0%
#200
b10 #
b10 2
b10 5
b10 6
1%
#201
0%
#202
b1 #
b1 2
b1 5
b1 6
1%
#203
0%
#204
10
1-
b0 #
b0 2
b0 5
b0 6
1%
#205
0%
#206
00
0-
b1 "
b1 1
b1 7
b1 8
b1001 #
b1001 2
b1001 5
b1001 6
1%
#207
0%
#208
b1000 #
b1000 2
b1000 5
b1000 6
1%
#209
0%
#210
b111 #
b111 2
b111 5
b111 6
1%
#211
0%
#212
b110 #
b110 2
b110 5
b110 6
1%
#213
0%
#214
b101 #
b101 2
b101 5
b101 6
1%
#215
0%
#216
b100 #
b100 2
b100 5
b100 6
1%
#217
0%
#218
b11 #
b11 2
b11 5
b11 6
1%
#219
0%
#220
b10 #
b10 2
b10 5
b10 6
1%
#221
0%
#222
b1 #
b1 2
b1 5
b1 6
1%
#223
0%
#224
10
1-
b0 #
b0 2
b0 5
b0 6
1%
#225
0%
#226
00
1,
0-
b0 "
b0 1
b0 7
b0 8
b1001 #
b1001 2
b1001 5
b1001 6
1%
#227
0%
#228
b1000 #
b1000 2
b1000 5
b1000 6
1%
#229
0%
#230
b111 #
b111 2
b111 5
b111 6
1%
#231
0%
#232
b110 #
b110 2
b110 5
b110 6
1%
#233
0%
#234
b101 #
b101 2
b101 5
b101 6
1%
#235
0%
#236
b100 #
b100 2
b100 5
b100 6
1%
#237
0%
#238
b11 #
b11 2
b11 5
b11 6
1%
#239
0%
#240
b10 #
b10 2
b10 5
b10 6
1%
#241
0%
#242
b1 #
b1 2
b1 5
b1 6
1%
#243
0%
#244
1.
1/
1!
10
1-
b0 #
b0 2
b0 5
b0 6
1%
#245
0%
#246
0.
0!
0/
00
0+
0,
0-
b1001 $
b1001 3
b1001 9
b101 "
b101 1
b101 7
b101 8
b1001 #
b1001 2
b1001 5
b1001 6
1%
#247
0%
#248
b1000 #
b1000 2
b1000 5
b1000 6
1%
#249
0%
#250
b111 #
b111 2
b111 5
b111 6
1%
#251
0%
#252
b110 #
b110 2
b110 5
b110 6
1%
#253
0%
#254
b101 #
b101 2
b101 5
b101 6
1%
#255
0%
#256
b100 #
b100 2
b100 5
b100 6
1%
#257
0%
#258
b11 #
b11 2
b11 5
b11 6
1%
#259
0%
#260
b10 #
b10 2
b10 5
b10 6
1%
#261
0%
#262
b1 #
b1 2
b1 5
b1 6
1%
#263
0%
#264
10
1-
b0 #
b0 2
b0 5
b0 6
1%
#265
0%
#266
00
0-
b100 "
b100 1
b100 7
b100 8
b1001 #
b1001 2
b1001 5
b1001 6
1%
#267
0%
#268
b1000 #
b1000 2
b1000 5
b1000 6
1%
#269
0%
#270
b111 #
b111 2
b111 5
b111 6
1%
#271
0%
#272
b110 #
b110 2
b110 5
b110 6
1%
#273
0%
#274
b101 #
b101 2
b101 5
b101 6
1%
#275
0%
#276
b100 #
b100 2
b100 5
b100 6
1%
#277
0%
#278
b11 #
b11 2
b11 5
b11 6
1%
#279
0%
#280
b10 #
b10 2
b10 5
b10 6
1%
#281
0%
#282
b1 #
b1 2
b1 5
b1 6
1%
#283
0%
#284
10
1-
b0 #
b0 2
b0 5
b0 6
1%
#285
0%
#286
00
0-
b11 "
b11 1
b11 7
b11 8
b1001 #
b1001 2
b1001 5
b1001 6
1%
#287
0%
#288
b1000 #
b1000 2
b1000 5
b1000 6
1%
#289
0%
#290
b111 #
b111 2
b111 5
b111 6
1%
#291
0%
#292
b110 #
b110 2
b110 5
b110 6
1%
#293
0%
#294
b101 #
b101 2
b101 5
b101 6
1%
#295
0%
#296
b100 #
b100 2
b100 5
b100 6
1%
#297
0%
#298
b11 #
b11 2
b11 5
b11 6
1%
#299
0%
#300
b10 #
b10 2
b10 5
b10 6
1%
#301
0%
#302
b1 #
b1 2
b1 5
b1 6
1%
#303
0%
#304
10
1-
b0 #
b0 2
b0 5
b0 6
1%
#305
0%
#306
00
0-
b10 "
b10 1
b10 7
b10 8
b1001 #
b1001 2
b1001 5
b1001 6
1%
#307
0%
#308
b1000 #
b1000 2
b1000 5
b1000 6
1%
#309
0%
#310
b111 #
b111 2
b111 5
b111 6
1%
#311
0%
#312
b110 #
b110 2
b110 5
b110 6
1%
#313
0%
#314
b101 #
b101 2
b101 5
b101 6
1%
#315
0%
#316
b100 #
b100 2
b100 5
b100 6
1%
#317
0%
#318
b11 #
b11 2
b11 5
b11 6
1%
#319
0%
#320
b10 #
b10 2
b10 5
b10 6
1%
#321
0%
#322
b1 #
b1 2
b1 5
b1 6
1%
#323
0%
#324
10
1-
b0 #
b0 2
b0 5
b0 6
1%
#325
0%
#326
00
0-
b1 "
b1 1
b1 7
b1 8
b1001 #
b1001 2
b1001 5
b1001 6
1%
#327
0%
#328
b1000 #
b1000 2
b1000 5
b1000 6
1%
#329
0%
#330
b111 #
b111 2
b111 5
b111 6
1%
#331
0%
#332
b110 #
b110 2
b110 5
b110 6
1%
#333
0%
#334
b101 #
b101 2
b101 5
b101 6
1%
#335
0%
#336
b100 #
b100 2
b100 5
b100 6
1%
#337
0%
#338
b11 #
b11 2
b11 5
b11 6
1%
#339
0%
#340
b10 #
b10 2
b10 5
b10 6
1%
#341
0%
#342
b1 #
b1 2
b1 5
b1 6
1%
#343
0%
#344
10
1-
b0 #
b0 2
b0 5
b0 6
1%
#345
0%
#346
00
1,
0-
b0 "
b0 1
b0 7
b0 8
b1001 #
b1001 2
b1001 5
b1001 6
1%
#347
0%
#348
b1000 #
b1000 2
b1000 5
b1000 6
1%
#349
0%
#350
b111 #
b111 2
b111 5
b111 6
1%
#351
0%
#352
b110 #
b110 2
b110 5
b110 6
1%
#353
0%
#354
b101 #
b101 2
b101 5
b101 6
1%
#355
0%
#356
b100 #
b100 2
b100 5
b100 6
1%
#357
0%
#358
b11 #
b11 2
b11 5
b11 6
1%
#359
0%
#360
b10 #
b10 2
b10 5
b10 6
1%
#361
0%
#362
b1 #
b1 2
b1 5
b1 6
1%
#363
0%
#364
1/
10
1-
b0 #
b0 2
b0 5
b0 6
1%
#365
0%
#366
0/
00
0,
0-
b1000 $
b1000 3
b1000 9
b101 "
b101 1
b101 7
b101 8
b1001 #
b1001 2
b1001 5
b1001 6
1%
#367
0%
#368
b1000 #
b1000 2
b1000 5
b1000 6
1%
#369
0%
#370
b111 #
b111 2
b111 5
b111 6
1%
#371
0%
#372
b110 #
b110 2
b110 5
b110 6
1%
#373
0%
#374
b101 #
b101 2
b101 5
b101 6
1%
#375
0%
#376
b100 #
b100 2
b100 5
b100 6
1%
#377
0%
#378
b11 #
b11 2
b11 5
b11 6
1%
#379
0%
#380
b10 #
b10 2
b10 5
b10 6
1%
#381
0%
#382
b1 #
b1 2
b1 5
b1 6
1%
#383
0%
#384
10
1-
b0 #
b0 2
b0 5
b0 6
1%
#385
0%
#386
00
0-
b100 "
b100 1
b100 7
b100 8
b1001 #
b1001 2
b1001 5
b1001 6
1%
#387
0%
#388
b1000 #
b1000 2
b1000 5
b1000 6
1%
#389
0%
#390
b111 #
b111 2
b111 5
b111 6
1%
#391
0%
#392
b110 #
b110 2
b110 5
b110 6
1%
#393
0%
#394
b101 #
b101 2
b101 5
b101 6
1%
#395
0%
#396
b100 #
b100 2
b100 5
b100 6
1%
#397
0%
#398
b11 #
b11 2
b11 5
b11 6
1%
#399
0%
#400
b10 #
b10 2
b10 5
b10 6
1%
#401
0%
#402
b1 #
b1 2
b1 5
b1 6
1%
#403
0%
#404
10
1-
b0 #
b0 2
b0 5
b0 6
1%
#405
0%
#406
00
0-
b11 "
b11 1
b11 7
b11 8
b1001 #
b1001 2
b1001 5
b1001 6
1%
#407
0%
#408
b1000 #
b1000 2
b1000 5
b1000 6
1%
#409
0%
#410
b111 #
b111 2
b111 5
b111 6
1%
#411
0%
#412
b110 #
b110 2
b110 5
b110 6
1%
#413
0%
#414
b101 #
b101 2
b101 5
b101 6
1%
#415
0%
#416
b100 #
b100 2
b100 5
b100 6
1%
#417
0%
#418
b11 #
b11 2
b11 5
b11 6
1%
#419
0%
#420
b10 #
b10 2
b10 5
b10 6
1%
#421
0%
#422
b1 #
b1 2
b1 5
b1 6
1%
#423
0%
#424
10
1-
b0 #
b0 2
b0 5
b0 6
1%
#425
0%
#426
00
0-
b10 "
b10 1
b10 7
b10 8
b1001 #
b1001 2
b1001 5
b1001 6
1%
#427
0%
#428
b1000 #
b1000 2
b1000 5
b1000 6
1%
#429
0%
#430
b111 #
b111 2
b111 5
b111 6
1%
#431
0%
#432
b110 #
b110 2
b110 5
b110 6
1%
#433
0%
#434
b101 #
b101 2
b101 5
b101 6
1%
#435
0%
#436
b100 #
b100 2
b100 5
b100 6
1%
#437
0%
#438
b11 #
b11 2
b11 5
b11 6
1%
#439
0%
#440
b10 #
b10 2
b10 5
b10 6
1%
#441
0%
#442
b1 #
b1 2
b1 5
b1 6
1%
#443
0%
#444
10
1-
b0 #
b0 2
b0 5
b0 6
1%
#445
0%
#446
00
0-
b1 "
b1 1
b1 7
b1 8
b1001 #
b1001 2
b1001 5
b1001 6
1%
#447
0%
#448
b1000 #
b1000 2
b1000 5
b1000 6
1%
#449
0%
#450
b111 #
b111 2
b111 5
b111 6
1%
#451
0%
#452
b110 #
b110 2
b110 5
b110 6
1%
#453
0%
#454
b101 #
b101 2
b101 5
b101 6
1%
#455
0%
#456
b100 #
b100 2
b100 5
b100 6
1%
#457
0%
#458
b11 #
b11 2
b11 5
b11 6
1%
#459
0%
#460
b10 #
b10 2
b10 5
b10 6
1%
#461
0%
#462
b1 #
b1 2
b1 5
b1 6
1%
#463
0%
#464
10
1-
b0 #
b0 2
b0 5
b0 6
1%
#465
0%
#466
00
1,
0-
b0 "
b0 1
b0 7
b0 8
b1001 #
b1001 2
b1001 5
b1001 6
1%
#467
0%
#468
b1000 #
b1000 2
b1000 5
b1000 6
1%
#469
0%
#470
b111 #
b111 2
b111 5
b111 6
1%
#471
0%
#472
b110 #
b110 2
b110 5
b110 6
1%
#473
0%
#474
b101 #
b101 2
b101 5
b101 6
1%
#475
0%
#476
b100 #
b100 2
b100 5
b100 6
1%
#477
0%
#478
b11 #
b11 2
b11 5
b11 6
1%
#479
0%
#480
b10 #
b10 2
b10 5
b10 6
1%
#481
0%
#482
b1 #
b1 2
b1 5
b1 6
1%
#483
0%
#484
1/
10
1-
b0 #
b0 2
b0 5
b0 6
1%
#485
0%
#486
0/
00
0,
0-
b111 $
b111 3
b111 9
b101 "
b101 1
b101 7
b101 8
b1001 #
b1001 2
b1001 5
b1001 6
1%
#487
0%
#488
b1000 #
b1000 2
b1000 5
b1000 6
1%
#489
0%
#490
b111 #
b111 2
b111 5
b111 6
1%
#491
0%
#492
b110 #
b110 2
b110 5
b110 6
1%
#493
0%
#494
b101 #
b101 2
b101 5
b101 6
1%
#495
0%
#496
b100 #
b100 2
b100 5
b100 6
1%
#497
0%
#498
b11 #
b11 2
b11 5
b11 6
1%
#499
0%
#500
b10 #
b10 2
b10 5
b10 6
1%
#501
0%
#502
b1 #
b1 2
b1 5
b1 6
1%
#503
0%
#504
10
1-
b0 #
b0 2
b0 5
b0 6
1%
#505
0%
#506
00
0-
b100 "
b100 1
b100 7
b100 8
b1001 #
b1001 2
b1001 5
b1001 6
1%
#507
0%
#508
b1000 #
b1000 2
b1000 5
b1000 6
1%
#509
0%
#510
b111 #
b111 2
b111 5
b111 6
1%
#511
0%
#512
b110 #
b110 2
b110 5
b110 6
1%
#513
0%
#514
b101 #
b101 2
b101 5
b101 6
1%
#515
0%
#516
b100 #
b100 2
b100 5
b100 6
1%
#517
0%
#518
b11 #
b11 2
b11 5
b11 6
1%
#519
0%
#520
b10 #
b10 2
b10 5
b10 6
1%
#521
0%
#522
b1 #
b1 2
b1 5
b1 6
1%
#523
0%
#524
10
1-
b0 #
b0 2
b0 5
b0 6
1%
#525
0%
#526
00
0-
b11 "
b11 1
b11 7
b11 8
b1001 #
b1001 2
b1001 5
b1001 6
1%
#527
0%
#528
b1000 #
b1000 2
b1000 5
b1000 6
1%
#529
0%
#530
b111 #
b111 2
b111 5
b111 6
1%
#531
0%
#532
b110 #
b110 2
b110 5
b110 6
1%
#533
0%
#534
b101 #
b101 2
b101 5
b101 6
1%
#535
0%
#536
b100 #
b100 2
b100 5
b100 6
1%
#537
0%
#538
b11 #
b11 2
b11 5
b11 6
1%
#539
0%
#540
b10 #
b10 2
b10 5
b10 6
1%
#541
0%
#542
b1 #
b1 2
b1 5
b1 6
1%
#543
0%
#544
10
1-
b0 #
b0 2
b0 5
b0 6
1%
#545
0%
#546
00
0-
b10 "
b10 1
b10 7
b10 8
b1001 #
b1001 2
b1001 5
b1001 6
1%
#547
0%
#548
b1000 #
b1000 2
b1000 5
b1000 6
1%
#549
0%
#550
b111 #
b111 2
b111 5
b111 6
1%
#551
0%
#552
b110 #
b110 2
b110 5
b110 6
1%
#553
0%
#554
b101 #
b101 2
b101 5
b101 6
1%
#555
0%
#556
b100 #
b100 2
b100 5
b100 6
1%
#557
0%
#558
b11 #
b11 2
b11 5
b11 6
1%
#559
0%
#560
b10 #
b10 2
b10 5
b10 6
1%
#561
0%
#562
b1 #
b1 2
b1 5
b1 6
1%
#563
0%
#564
10
1-
b0 #
b0 2
b0 5
b0 6
1%
#565
0%
#566
00
0-
b1 "
b1 1
b1 7
b1 8
b1001 #
b1001 2
b1001 5
b1001 6
1%
#567
0%
#568
b1000 #
b1000 2
b1000 5
b1000 6
1%
#569
0%
#570
b111 #
b111 2
b111 5
b111 6
1%
#571
0%
#572
b110 #
b110 2
b110 5
b110 6
1%
#573
0%
#574
b101 #
b101 2
b101 5
b101 6
1%
#575
0%
#576
b100 #
b100 2
b100 5
b100 6
1%
#577
0%
#578
b11 #
b11 2
b11 5
b11 6
1%
#579
0%
#580
b10 #
b10 2
b10 5
b10 6
1%
#581
0%
#582
b1 #
b1 2
b1 5
b1 6
1%
#583
0%
#584
10
1-
b0 #
b0 2
b0 5
b0 6
1%
#585
0%
#586
00
1,
0-
b0 "
b0 1
b0 7
b0 8
b1001 #
b1001 2
b1001 5
b1001 6
1%
#587
0%
#588
b1000 #
b1000 2
b1000 5
b1000 6
1%
#589
0%
#590
b111 #
b111 2
b111 5
b111 6
1%
#591
0%
#592
b110 #
b110 2
b110 5
b110 6
1%
#593
0%
#594
b101 #
b101 2
b101 5
b101 6
1%
#595
0%
#596
b100 #
b100 2
b100 5
b100 6
1%
#597
0%
#598
b11 #
b11 2
b11 5
b11 6
1%
#599
0%
#600
b10 #
b10 2
b10 5
b10 6
1%
#601
0%
#602
b1 #
b1 2
b1 5
b1 6
1%
#603
0%
#604
1/
10
1-
b0 #
b0 2
b0 5
b0 6
1%
#605
0%
#606
0/
00
0,
0-
b110 $
b110 3
b110 9
b101 "
b101 1
b101 7
b101 8
b1001 #
b1001 2
b1001 5
b1001 6
1%
#607
0%
#608
b1000 #
b1000 2
b1000 5
b1000 6
1%
#609
0%
#610
b111 #
b111 2
b111 5
b111 6
1%
#611
0%
#612
b110 #
b110 2
b110 5
b110 6
1%
#613
0%
#614
b101 #
b101 2
b101 5
b101 6
1%
#615
0%
#616
b100 #
b100 2
b100 5
b100 6
1%
#617
0%
#618
b11 #
b11 2
b11 5
b11 6
1%
#619
0%
#620
b10 #
b10 2
b10 5
b10 6
1%
#621
0%
#622
b1 #
b1 2
b1 5
b1 6
1%
#623
0%
#624
10
1-
b0 #
b0 2
b0 5
b0 6
1%
#625
0%
#626
00
0-
b100 "
b100 1
b100 7
b100 8
b1001 #
b1001 2
b1001 5
b1001 6
1%
#627
0%
#628
b1000 #
b1000 2
b1000 5
b1000 6
1%
#629
0%
#630
b111 #
b111 2
b111 5
b111 6
1%
#631
0%
#632
b110 #
b110 2
b110 5
b110 6
1%
#633
0%
#634
b101 #
b101 2
b101 5
b101 6
1%
#635
0%
#636
b100 #
b100 2
b100 5
b100 6
1%
#637
0%
#638
b11 #
b11 2
b11 5
b11 6
1%
#639
0%
#640
b10 #
b10 2
b10 5
b10 6
1%
#641
0%
#642
b1 #
b1 2
b1 5
b1 6
1%
#643
0%
#644
10
1-
b0 #
b0 2
b0 5
b0 6
1%
#645
0%
#646
00
0-
b11 "
b11 1
b11 7
b11 8
b1001 #
b1001 2
b1001 5
b1001 6
1%
#647
0%
#648
b1000 #
b1000 2
b1000 5
b1000 6
1%
#649
0%
#650
b111 #
b111 2
b111 5
b111 6
1%
#651
0%
#652
b110 #
b110 2
b110 5
b110 6
1%
#653
0%
#654
b101 #
b101 2
b101 5
b101 6
1%
#655
0%
#656
b100 #
b100 2
b100 5
b100 6
1%
#657
0%
#658
b11 #
b11 2
b11 5
b11 6
1%
#659
0%
#660
b10 #
b10 2
b10 5
b10 6
1%
#661
0%
#662
b1 #
b1 2
b1 5
b1 6
1%
#663
0%
#664
10
1-
b0 #
b0 2
b0 5
b0 6
1%
#665
0%
