P3/nivel 1/nivel 2/Entrada de timer e controle/nivel 3/Multiplexador/mux.v
module mux(
  input wire sel,
  input wire non_recycling_counter_output,
  input wire clk_1Hz,
  output reg pgt_1Hz
);

  always @* begin
    pgt_1Hz = (sel == 0) ? non_recycling_counter_output : clk_1Hz;
  end

endmodule

P3/nivel 1/nivel 2/Entrada de timer e controle/nivel 3/contador nao reciclavel/non_recycling_counter.v
module non_recycling_counter(
    input wire clock,
    input wire clear,
    output wire non_recycling_counter_output
);

    reg [2:0] counter;
    initial counter = 0;

    always @(posedge clock or posedge clear) begin
        if (clear) begin
            counter <= 0;
        end else if (counter < 7) begin
            counter <= counter + 1;
        end
    end

    assign non_recycling_counter_output = (counter >= 4);

endmodule

P3/nivel 1/nivel 2/Entrada de timer e controle/Nível 3/divisor frequência 100/div_freq_100.v

`define END_OF_COUNT Q == 49 //6'b11_0010

module div_freq_100 (input wire clk,
                    output reg clk_1Hz);

    reg [5:0] Q = 0;
    initial clk_1Hz = 0;

    always @(posedge clk)

        if (END_OF_COUNT) begin
        
            clk_1Hz <= ~clk_1Hz;
            Q <= 0;

        end else
            Q <= Q+1;
    

endmodule

`undef END_OF_COUNT

P3/nivel 1/nivel 2/Entrada de timer e controle/nivel 3/codificador prioritario/prioritary_encoder.v
module prioritary_encoder  (keypad, enablen, D, valid);

    input wire[9:0] keypad;
    input wire enablen;

    output reg[3:0] D;
    output wire valid;
    initial D = 4'hF;


    always @(keypad)
        if (!enablen)
            D = (keypad == 10'b0000000001)? 0:
                (keypad == 10'b0000000010)? 1:
                (keypad == 10'b0000000100)? 2:
                (keypad == 10'b0000001000)? 3:
                (keypad == 10'b0000010000)? 4:
                (keypad == 10'b0000100000)? 5:
                (keypad == 10'b0001000000)? 6:
                (keypad == 10'b0010000000)? 7:
                (keypad == 10'b0100000000)? 8:
                (keypad == 10'b1000000000)? 9:
                4'hF;

    assign valid = (enablen |
                    D == 4'hF);

endmodule

P3/nivel 1/nivel 2/Entrada de timer e controle/encoder_timer_input_control.v
`include "nivel 2\\Entrada de timer e controle\\nivel 3\\divisor frequencia 100\\div_freq_100.v"
`include "nivel 2\\Entrada de timer e controle\\nivel 3\\codificador prioritario\\prioritary_encoder.v"
`include "nivel 2\\Entrada de timer e controle\\nivel 3\\contador nao reciclavel\\non_recycling_counter.v"
`include "nivel 2\\Entrada de timer e controle\\nivel 3\Multiplexador\\mux.v"

module encoder_timer_input_control (keypad, enablen, clk, D, loadn, pgt_1Hz);
       
    input wire[9:0] keypad;
    input wire enablen, clk;

    output [3:0] D;
    output wire loadn;
    output pgt_1Hz;

    wire clk_1Hz, single_edge;

       prioritary_encoder prioritary_encoder(keypad, enablen, D, loadn);
       div_freq_100 div_freq_100(clk, clk_1Hz);
       non_recycling_counter non_recycling_counter(clk, loadn, single_edge);
       mux mux(enablen, single_edge, clk_1Hz, pgt_1Hz);

endmodule

P3/nivel 1/nivel 2/Entrada de timer e controle/tb_encoder_timer_input_control.v
`timescale 1ms/1ns
`include "encoder_timer_input_control.v"

module tb_encoder_timer_input_control;
    reg[9:0] keypad;
    reg enablen;
    reg clk;
    wire[3:0] D_tb;
    wire loadn;
    wire pgt_1Hz;

    encoder_timer_input_control DUT
    (
        .keypad (keypad),
        .enablen (enablen),
        .clk (clk),
        .D (D_tb),
        .loadn (loadn),
        .pgt_1Hz (pgt_1Hz)
    );

    initial begin
        $dumpfile("tb_encoder_timer_input_control.vcd");
        $dumpvars(0, tb_encoder_timer_input_control);

        clk = 0;
        enablen = 0;
        keypad = 0;

        repeat(2) begin
            enablen = ~enablen;
            for (integer i = 0; i < 10; i = i+1) begin   
                keypad = 1 << i;
                repeat(20) #5 clk =~clk;
                keypad = 0;
                repeat(20) #5 clk =~clk;
            end
        end
        keypad = 10'h80;
        repeat(4) #5 clk =~clk;
        keypad = 10'h84;
        repeat(6) #5 clk =~clk;

    end

endmodule

P3/nivel 1/nivel 2/Entrada de timer e controle/tb_encoder_timer_input_control.vcd
$date
	Sun Sep 24 16:57:09 2023
$end
$version
	Icarus Verilog
$end
$timescale
	1ns
$end
$scope module tb_encoder_timer_input_control $end
$var wire 1 ! pgt_1Hz $end
$var wire 1 " loadn $end
$var wire 4 # D_tb [3:0] $end
$var reg 1 $ clk $end
$var reg 1 % enablen $end
$var reg 10 & keypad [9:0] $end
$scope module DUT $end
$var wire 1 $ clk $end
$var wire 1 % enablen $end
$var wire 10 ' keypad [9:0] $end
$var wire 1 ( single_edge $end
$var wire 1 ! pgt_1Hz $end
$var wire 1 " loadn $end
$var wire 1 ) clk_1Hz $end
$var wire 4 * D [3:0] $end
$scope module div_freq_100 $end
$var wire 1 $ clk $end
$var reg 6 + Q [5:0] $end
$var reg 1 ) clk_1Hz $end
$upscope $end
$scope module mux $end
$var wire 1 ) clk_1Hz $end
$var wire 1 % sel $end
$var wire 1 ( non_recycling_counter_output $end
$var reg 1 ! pgt_1Hz $end
$upscope $end
$scope module non_recycling_counter $end
$var wire 1 $ clock $end
$var wire 1 " clear $end
$var reg 3 , counter [2:0] $end
$var reg 1 ( non_recycling_counter_output $end
$upscope $end
$scope module prioritary_encoder $end
$var wire 1 % enablen $end
$var wire 10 - keypad [9:0] $end
$var wire 1 " valid $end
$var reg 4 . D [3:0] $end
$upscope $end
$upscope $end
$scope begin $ivl_for_loop0 $end
$var integer 32 / i [31:0] $end
$upscope $end
$upscope $end
$enddefinitions $end
$comment Show the parameter values. $end
$dumpall
$end
#0
$dumpvars
b0 /
bx .
b1 -
b0 ,
b0 +
bx *
0)
0(
b1 '
b1 &
1%
0$
bx #
1"
0!
$end
#5000000
b1 +
1$
#10000000
0$
#15000000
b10 +
1$
#20000000
0$
#25000000
b11 +
1$
#30000000
0$
#35000000
b100 +
1$
#40000000
0$
#45000000
b101 +
1$
#50000000
0$
#55000000
b110 +
1$
#60000000
0$
#65000000
b111 +
1$
#70000000
0$
#75000000
b1000 +
1$
#80000000
0$
#85000000
b1001 +
1$
#90000000
0$
#95000000
b1010 +
1$
#100000000
b0 &
b0 '
b0 -
0$
#105000000
b1011 +
1$
#110000000
0$
#115000000
b1100 +
1$
#120000000
0$
#125000000
b1101 +
1$
#130000000
0$
#135000000
b1110 +
1$
#140000000
0$
#145000000
b1111 +
1$
#150000000
0$
#155000000
b10000 +
1$
#160000000
0$
#165000000
b10001 +
1$
#170000000
0$
#175000000
b10010 +
1$
#180000000
0$
#185000000
b10011 +
1$
#190000000
0$
#195000000
b10100 +
1$
#200000000
b10 &
b10 '
b10 -
b1 /
0$
#205000000
b10101 +
1$
#210000000
0$
#215000000
b10110 +
1$
#220000000
0$
#225000000
b10111 +
1$
#230000000
0$
#235000000
b11000 +
1$
#240000000
0$
#245000000
b11001 +
1$
#250000000
0$
#255000000
b11010 +
1$
#260000000
0$
#265000000
b11011 +
1$
#270000000
0$
#275000000
b11100 +
1$
#280000000
0$
#285000000
b11101 +
1$
#290000000
0$
#295000000
b11110 +
1$
#300000000
b0 &
b0 '
b0 -
0$
#305000000
b11111 +
1$
#310000000
0$
#315000000
b100000 +
1$
#320000000
0$
#325000000
b100001 +
1$
#330000000
0$
#335000000
b100010 +
1$
#340000000
0$
#345000000
b100011 +
1$
#350000000
0$
#355000000
b100100 +
1$
#360000000
0$
#365000000
b100101 +
1$
#370000000
0$
#375000000
b100110 +
1$
#380000000
0$
#385000000
b100111 +
1$
#390000000
0$
#395000000
b101000 +
1$
#400000000
b100 &
b100 '
b100 -
b10 /
0$
#405000000
b101001 +
1$
#410000000
0$
#415000000
b101010 +
1$
#420000000
0$
#425000000
b101011 +
1$
#430000000
0$
#435000000
b101100 +
1$
#440000000
0$
#445000000
b101101 +
1$
#450000000
0$
#455000000
b101110 +
1$
#460000000
0$
#465000000
b101111 +
1$
#470000000
0$
#475000000
b110000 +
1$
#480000000
0$
#485000000
b110001 +
1$
#490000000
0$
#495000000
1!
b0 +
1)
1$
#500000000
b0 &
b0 '
b0 -
0$
#505000000
b1 +
1$
#510000000
0$
#515000000
b10 +
1$
#520000000
0$
#525000000
b11 +
1$
#530000000
0$
#535000000
b100 +
1$
#540000000
0$
#545000000
b101 +
1$
#550000000
0$
#555000000
b110 +
1$
#560000000
0$
#565000000
b111 +
1$
#570000000
0$
#575000000
b1000 +
1$
#580000000
0$
#585000000
b1001 +
1$
#590000000
0$
#595000000
b1010 +
1$
#600000000
b1000 &
b1000 '
b1000 -
b11 /
0$
#605000000
b1011 +
1$
#610000000
0$
#615000000
b1100 +
1$
#620000000
0$
#625000000
b1101 +
1$
#630000000
0$
#635000000
b1110 +
1$
#640000000
0$
#645000000
b1111 +
1$
#650000000
0$
#655000000
b10000 +
1$
#660000000
0$
#665000000
b10001 +
1$
#670000000
0$
#675000000
b10010 +
1$
#680000000
0$
#685000000
b10011 +
1$
#690000000
0$
#695000000
b10100 +
1$
#700000000
b0 &
b0 '
b0 -
0$
#705000000
b10101 +
1$
#710000000
0$
#715000000
b10110 +
1$
#720000000
0$
#725000000
b10111 +
1$
#730000000
0$
#735000000
b11000 +
1$
#740000000
0$
#745000000
b11001 +
1$
#750000000
0$
#755000000
b11010 +
1$
#760000000
0$
#765000000
b11011 +
1$
#770000000
0$
#775000000
b11100 +
1$
#780000000
0$
#785000000
b11101 +
1$
#790000000
0$
#795000000
b11110 +
1$
#800000000
b10000 &
b10000 '
b10000 -
b100 /
0$
#805000000
b11111 +
1$
#810000000
0$
#815000000
b100000 +
1$
#820000000
0$
#825000000
b100001 +
1$
#830000000
0$
#835000000
b100010 +
1$
#840000000
0$
#845000000
b100011 +
1$
#850000000
0$
#855000000
b100100 +
1$
#860000000
0$
#865000000
b100101 +
1$
#870000000
0$
#875000000
b100110 +
1$
#880000000
0$
#885000000
b100111 +
1$
#890000000
0$
#895000000
b101000 +
1$
#900000000
b0 &
b0 '
b0 -
0$
#905000000
b101001 +
1$
#910000000
0$
#915000000
b101010 +
1$
#920000000
0$
#925000000
b101011 +
1$
#930000000
0$
#935000000
b101100 +
1$
#940000000
0$
#945000000
b101101 +
1$
#950000000
0$
#955000000
b101110 +
1$
#960000000
0$
#965000000
b101111 +
1$
#970000000
0$
#975000000
b110000 +
1$
#980000000
0$
#985000000
b110001 +
1$
#990000000
0$
#995000000
0!
b0 +
0)
1$
#1000000000
b100000 &
b100000 '
b100000 -
b101 /
0$
#1005000000
b1 +
1$
#1010000000
0$
#1015000000
b10 +
1$
#1020000000
0$
#1025000000
b11 +
1$
#1030000000
0$
#1035000000
b100 +
1$
#1040000000
0$
#1045000000
b101 +
1$
#1050000000
0$
#1055000000
b110 +
1$
#1060000000
0$
#1065000000
b111 +
1$
#1070000000
0$
#1075000000
b1000 +
1$
#1080000000
0$
#1085000000
b1001 +
1$
#1090000000
0$
#1095000000
b1010 +
1$
#1100000000
b0 &
b0 '
b0 -
0$
#1105000000
b1011 +
1$
#1110000000
0$
#1115000000
b1100 +
1$
#1120000000
0$
#1125000000
b1101 +
1$
#1130000000
0$
#1135000000
b1110 +
1$
#1140000000
0$
#1145000000
b1111 +
1$
#1150000000
0$
#1155000000
b10000 +
1$
#1160000000
0$
#1165000000
b10001 +
1$
#1170000000
0$
#1175000000
b10010 +
1$
#1180000000
0$
#1185000000
b10011 +
1$
#1190000000
0$
#1195000000
b10100 +
1$
#1200000000
b1000000 &
b1000000 '
b1000000 -
b110 /
0$
#1205000000
b10101 +
1$
#1210000000
0$
#1215000000
b10110 +
1$
#1220000000
0$
#1225000000
b10111 +
1$
#1230000000
0$
#1235000000
b11000 +
1$
#1240000000
0$
#1245000000
b11001 +
1$
#1250000000
0$
#1255000000
b11010 +
1$
#1260000000
0$
#1265000000
b11011 +
1$
#1270000000
0$
#1275000000
b11100 +
1$
#1280000000
0$
#1285000000
b11101 +
1$
#1290000000
0$
#1295000000
b11110 +
1$
#1300000000
b0 &
b0 '
b0 -
0$
#1305000000
b11111 +
1$
#1310000000
0$
#1315000000
b100000 +
1$
#1320000000
0$
#1325000000
b100001 +
1$
#1330000000
0$
#1335000000
b100010 +
1$
#1340000000
0$
#1345000000
b100011 +
1$
#1350000000
0$
#1355000000
b100100 +
1$
#1360000000
0$
#1365000000
b100101 +
1$
#1370000000
0$
#1375000000
b100110 +
1$
#1380000000
0$
#1385000000
b100111 +
1$
#1390000000
0$
#1395000000
b101000 +
1$
#1400000000
b10000000 &
b10000000 '
b10000000 -
b111 /
0$
#1405000000
b101001 +
1$
#1410000000
0$
#1415000000
b101010 +
1$
#1420000000
0$
#1425000000
b101011 +
1$
#1430000000
0$
#1435000000
b101100 +
1$
#1440000000
0$
#1445000000
b101101 +
1$
#1450000000
0$
#1455000000
b101110 +
1$
#1460000000
0$
#1465000000
b101111 +
1$
#1470000000
0$
#1475000000
b110000 +
1$
#1480000000
0$
#1485000000
b110001 +
1$
#1490000000
0$
#1495000000
1!
b0 +
1)
1$
#1500000000
b0 &
b0 '
b0 -
0$
#1505000000
b1 +
1$
#1510000000
0$
#1515000000
b10 +
1$
#1520000000
0$
#1525000000
b11 +
1$
#1530000000
0$
#1535000000
b100 +
1$
#1540000000
0$
#1545000000
b101 +
1$
#1550000000
0$
#1555000000
b110 +
1$
#1560000000
0$
#1565000000
b111 +
1$
#1570000000
0$
#1575000000
b1000 +
1$
#1580000000
0$
#1585000000
b1001 +
1$
#1590000000
0$
#1595000000
b1010 +
1$
#1600000000
b100000000 &
b100000000 '
b100000000 -
b1000 /
0$
#1605000000
b1011 +
1$
#1610000000
0$
#1615000000
b1100 +
1$
#1620000000
0$
#1625000000
b1101 +
1$
#1630000000
0$
#1635000000
b1110 +
1$
#1640000000
0$
#1645000000
b1111 +
1$
#1650000000
0$
#1655000000
b10000 +
1$
#1660000000
0$
#1665000000
b10001 +
1$
#1670000000
0$
#1675000000
b10010 +
1$
#1680000000
0$
#1685000000
b10011 +
1$
#1690000000
0$
#1695000000
b10100 +
1$
#1700000000
b0 &
b0 '
b0 -
0$
#1705000000
b10101 +
1$
#1710000000
0$
#1715000000
b10110 +
1$
#1720000000
0$
#1725000000
b10111 +
1$
#1730000000
0$
#1735000000
b11000 +
1$
#1740000000
0$
#1745000000
b11001 +
1$
#1750000000
0$
#1755000000
b11010 +
1$
#1760000000
0$
#1765000000
b11011 +
1$
#1770000000
0$
#1775000000
b11100 +
1$
#1780000000
0$
#1785000000
b11101 +
1$
#1790000000
0$
#1795000000
b11110 +
1$
#1800000000
b1000000000 &
b1000000000 '
b1000000000 -
b1001 /
0$
#1805000000
b11111 +
1$
#1810000000
0$
#1815000000
b100000 +
1$
#1820000000
0$
#1825000000
b100001 +
1$
#1830000000
0$
#1835000000
b100010 +
1$
#1840000000
0$
#1845000000
b100011 +
1$
#1850000000
0$
#1855000000
b100100 +
1$
#1860000000
0$
#1865000000
b100101 +
1$
#1870000000
0$
#1875000000
b100110 +
1$
#1880000000
0$
#1885000000
b100111 +
1$
#1890000000
0$
#1895000000
b101000 +
1$
#1900000000
b0 &
b0 '
b0 -
0$
#1905000000
b101001 +
1$
#1910000000
0$
#1915000000
b101010 +
1$
#1920000000
0$
#1925000000
b101011 +
1$
#1930000000
0$
#1935000000
b101100 +
1$
#1940000000
0$
#1945000000
b101101 +
1$
#1950000000
0$
#1955000000
b101110 +
1$
#1960000000
0$
#1965000000
b101111 +
1$
#1970000000
0$
#1975000000
b110000 +
1$
#1980000000
0$
#1985000000
b110001 +
1$
#1990000000
0$
#1995000000
0!
b0 +
0)
1$
#2000000000
b0 #
b0 *
b0 .
0"
b1 &
b1 '
b1 -
0%
b0 /
0$
#2005000000
b1 +
b1 ,
1$
#2010000000
0$
#2015000000
b10 +
b10 ,
1$
#2020000000
0$
#2025000000
b11 +
b11 ,
1$
#2030000000
0$
#2035000000
1!
b100 +
1(
b100 ,
1$
#2040000000
0$
#2045000000
b101 +
b101 ,
1$
#2050000000
0$
#2055000000
b110 +
b110 ,
1$
#2060000000
0$
#2065000000
b111 +
b111 ,
1$
#2070000000
0$
#2075000000
b1000 +
1$
#2080000000
0$
#2085000000
b1001 +
1$
#2090000000
0$
#2095000000
b1010 +
1$
#2100000000
0!
0(
b0 ,
1"
b1111 #
b1111 *
b1111 .
b0 &
b0 '
b0 -
0$
#2105000000
b1011 +
1$
#2110000000
0$
#2115000000
b1100 +
1$
#2120000000
0$
#2125000000
b1101 +
1$
#2130000000
0$
#2135000000
b1110 +
1$
#2140000000
0$
#2145000000
b1111 +
1$
#2150000000
0$
#2155000000
b10000 +
1$
#2160000000
0$
#2165000000
b10001 +
1$
#2170000000
0$
#2175000000
b10010 +
1$
#2180000000
0$
#2185000000
b10011 +
1$
#2190000000
0$
#2195000000
b10100 +
1$
#2200000000
0"
b1 #
b1 *
b1 .
b10 &
b10 '
b10 -
b1 /
0$
#2205000000
b10101 +
b1 ,
1$
#2210000000
0$
#2215000000
b10110 +
b10 ,
1$
#2220000000
0$
#2225000000
b10111 +
b11 ,
1$
#2230000000
0$
#2235000000
1!
b11000 +
1(
b100 ,
1$
#2240000000
0$
#2245000000
b11001 +
b101 ,
1$
#2250000000
0$
#2255000000
b11010 +
b110 ,
1$
#2260000000
0$
#2265000000
b11011 +
b111 ,
1$
#2270000000
0$
#2275000000
b11100 +
1$
#2280000000
0$
#2285000000
b11101 +
1$
#2290000000
0$
#2295000000
b11110 +
1$
#2300000000
0!
0(
b0 ,
1"
b1111 #
b1111 *
b1111 .
b0 &
b0 '
b0 -
0$
#2305000000
b11111 +
1$
#2310000000
0$
#2315000000
b100000 +
1$
#2320000000
0$
#2325000000
b100001 +
1$
#2330000000
0$
#2335000000
b100010 +
1$
#2340000000
0$
#2345000000
b100011 +
1$
#2350000000
0$
#2355000000
b100100 +
1$
#2360000000
0$
#2365000000
b100101 +
1$
#2370000000
0$
#2375000000
b100110 +
1$
#2380000000
0$
#2385000000
b100111 +
1$
#2390000000
0$
#2395000000
b101000 +
1$
#2400000000
0"
b10 #
b10 *
b10 .
b100 &
b100 '
b100 -
b10 /
0$
#2405000000
b101001 +
b1 ,
1$
#2410000000
0$
#2415000000
b101010 +
b10 ,
1$
#2420000000
0$
#2425000000
b101011 +
b11 ,
1$
#2430000000
0$
#2435000000
1!
b101100 +
1(
b100 ,
1$
#2440000000
0$
#2445000000
b101101 +
b101 ,
1$
#2450000000
0$
#2455000000
b101110 +
b110 ,
1$
#2460000000
0$
#2465000000
b101111 +
b111 ,
1$
#2470000000
0$
#2475000000
b110000 +
1$
#2480000000
0$
#2485000000
b110001 +
1$
#2490000000
0$
#2495000000
b0 +
1)
1$
#2500000000
0!
0(
b0 ,
1"
b1111 #
b1111 *
b1111 .
b0 &
b0 '
b0 -
0$
#2505000000
b1 +
1$
#2510000000
0$
#2515000000
b10 +
1$
#2520000000
0$
#2525000000
b11 +
1$
#2530000000
0$
#2535000000
b100 +
1$
#2540000000
0$
#2545000000
b101 +
1$
#2550000000
0$
#2555000000
b110 +
1$
#2560000000
0$
#2565000000
b111 +
1$
#2570000000
0$
#2575000000
b1000 +
1$
#2580000000
0$
#2585000000
b1001 +
1$
#2590000000
0$
#2595000000
b1010 +
1$
#2600000000
0"
b11 #
b11 *
b11 .
b1000 &
b1000 '
b1000 -
b11 /
0$
#2605000000
b1011 +
b1 ,
1$
#2610000000
0$
#2615000000
b1100 +
b10 ,
1$
#2620000000
0$
#2625000000
b1101 +
b11 ,
1$
#2630000000
0$
#2635000000
1!
b1110 +
1(
b100 ,
1$
#2640000000
0$
#2645000000
b1111 +
b101 ,
1$
#2650000000
0$
#2655000000
b10000 +
b110 ,
1$
#2660000000
0$
#2665000000
b10001 +
b111 ,
1$
#2670000000
0$
#2675000000
b10010 +
1$
#2680000000
0$
#2685000000
b10011 +
1$
#2690000000
0$
#2695000000
b10100 +
1$
#2700000000
0!
0(
b0 ,
1"
b1111 #
b1111 *
b1111 .
b0 &
b0 '
b0 -
0$
#2705000000
b10101 +
1$
#2710000000
0$
#2715000000
b10110 +
1$
#2720000000
0$
#2725000000
b10111 +
1$
#2730000000
0$
#2735000000
b11000 +
1$
#2740000000
0$
#2745000000
b11001 +
1$
#2750000000
0$
#2755000000
b11010 +
1$
#2760000000
0$
#2765000000
b11011 +
1$
#2770000000
0$
#2775000000
b11100 +
1$
#2780000000
0$
#2785000000
b11101 +
1$
#2790000000
0$
#2795000000
b11110 +
1$
#2800000000
0"
b100 #
b100 *
b100 .
b10000 &
b10000 '
b10000 -
b100 /
0$
#2805000000
b11111 +
b1 ,
1$
#2810000000
0$
#2815000000
b100000 +
b10 ,
1$
#2820000000
0$
#2825000000
b100001 +
b11 ,
1$
#2830000000
0$
#2835000000
1!
b100010 +
1(
b100 ,
1$
#2840000000
0$
#2845000000
b100011 +
b101 ,
1$
#2850000000
0$
#2855000000
b100100 +
b110 ,
1$
#2860000000
0$
#2865000000
b100101 +
b111 ,
1$
#2870000000
0$
#2875000000
b100110 +
1$
#2880000000
0$
#2885000000
b100111 +
1$
#2890000000
0$
#2895000000
b101000 +
1$
#2900000000
0!
0(
b0 ,
1"
b1111 #
b1111 *
b1111 .
b0 &
b0 '
b0 -
0$
#2905000000
b101001 +
1$
#2910000000
0$
#2915000000
b101010 +
1$
#2920000000
0$
#2925000000
b101011 +
1$
#2930000000
0$
#2935000000
b101100 +
1$
#2940000000
0$
#2945000000
b101101 +
1$
#2950000000
0$
#2955000000
b101110 +
1$
#2960000000
0$
#2965000000
b101111 +
1$
#2970000000
0$
#2975000000
b110000 +
1$
#2980000000
0$
#2985000000
b110001 +
1$
#2990000000
0$
#2995000000
b0 +
0)
1$
#3000000000
0"
b101 #
b101 *
b101 .
b100000 &
b100000 '
b100000 -
b101 /
0$
#3005000000
b1 +
b1 ,
1$
#3010000000
0$
#3015000000
b10 +
b10 ,
1$
#3020000000
0$
#3025000000
b11 +
b11 ,
1$
#3030000000
0$
#3035000000
1!
b100 +
1(
b100 ,
1$
#3040000000
0$
#3045000000
b101 +
b101 ,
1$
#3050000000
0$
#3055000000
b110 +
b110 ,
1$
#3060000000
0$
#3065000000
b111 +
b111 ,
1$
#3070000000
0$
#3075000000
b1000 +
1$
#3080000000
0$
#3085000000
b1001 +
1$
#3090000000
0$
#3095000000
b1010 +
1$
#3100000000
0!
0(
b0 ,
1"
b1111 #
b1111 *
b1111 .
b0 &
b0 '
b0 -
0$
#3105000000
b1011 +
1$
#3110000000
0$
#3115000000
b1100 +
1$
#3120000000
0$
#3125000000
b1101 +
1$
#3130000000
0$
#3135000000
b1110 +
1$
#3140000000
0$
#3145000000
b1111 +
1$
#3150000000
0$
#3155000000
b10000 +
1$
#3160000000
0$
#3165000000
b10001 +
1$
#3170000000
0$
#3175000000
b10010 +
1$
#3180000000
0$
#3185000000
b10011 +
1$
#3190000000
0$
#3195000000
b10100 +
1$
#3200000000
0"
b110 #
b110 *
b110 .
b1000000 &
b1000000 '
b1000000 -
b110 /
0$
#3205000000
b10101 +
b1 ,
1$
#3210000000
0$
#3215000000
b10110 +
b10 ,
1$
#3220000000
0$
#3225000000
b10111 +
b11 ,
1$
#3230000000
0$
#3235000000
1!
b11000 +
1(
b100 ,
1$
#3240000000
0$
#3245000000
b11001 +
b101 ,
1$
#3250000000
0$
#3255000000
b11010 +
b110 ,
1$
#3260000000
0$
#3265000000
b11011 +
b111 ,
1$
#3270000000
0$
#3275000000
b11100 +
1$
#3280000000
0$
#3285000000
b11101 +
1$
#3290000000
0$
#3295000000
b11110 +
1$
#3300000000
0!
0(
b0 ,
1"
b1111 #
b1111 *
b1111 .
b0 &
b0 '
b0 -
0$
#3305000000
b11111 +
1$
#3310000000
0$
#3315000000
b100000 +
1$
#3320000000
0$
#3325000000
b100001 +
1$
#3330000000
0$
#3335000000
b100010 +
1$
#3340000000
0$
#3345000000
b100011 +
1$
#3350000000
0$
#3355000000
b100100 +
1$
#3360000000
0$
#3365000000
b100101 +
1$
#3370000000
0$
#3375000000
b100110 +
1$
#3380000000
0$
#3385000000
b100111 +
1$
#3390000000
0$
#3395000000
b101000 +
1$
#3400000000
0"
b111 #
b111 *
b111 .
b10000000 &
b10000000 '
b10000000 -
b111 /
0$
#3405000000
b101001 +
b1 ,
1$
#3410000000
0$
#3415000000
b101010 +
b10 ,
1$
#3420000000
0$
#3425000000
b101011 +
b11 ,
1$
#3430000000
0$
#3435000000
1!
b101100 +
1(
b100 ,
1$
#3440000000
0$
#3445000000
b101101 +
b101 ,
1$
#3450000000
0$
#3455000000
b101110 +
b110 ,
1$
#3460000000
0$
#3465000000
b101111 +
b111 ,
1$
#3470000000
0$
#3475000000
b110000 +
1$
#3480000000
0$
#3485000000
b110001 +
1$
#3490000000
0$
#3495000000
b0 +
1)
1$
#3500000000
0!
0(
b0 ,
1"
b1111 #
b1111 *
b1111 .
b0 &
b0 '
b0 -
0$
#3505000000
b1 +
1$
#3510000000
0$
#3515000000
b10 +
1$
#3520000000
0$
#3525000000
b11 +
1$
#3530000000
0$
#3535000000
b100 +
1$
#3540000000
0$
#3545000000
b101 +
1$
#3550000000
0$
#3555000000
b110 +
1$
#3560000000
0$
#3565000000
b111 +
1$
#3570000000
0$
#3575000000
b1000 +
1$
#3580000000
0$
#3585000000
b1001 +
1$
#3590000000
0$
#3595000000
b1010 +
1$
#3600000000
0"
b1000 #
b1000 *
b1000 .
b100000000 &
b100000000 '
b100000000 -
b1000 /
0$
#3605000000
b1011 +
b1 ,
1$
#3610000000
0$
#3615000000
b1100 +
b10 ,
1$
#3620000000
0$
#3625000000
b1101 +
b11 ,
1$
#3630000000
0$
#3635000000
1!
b1110 +
1(
b100 ,
1$
#3640000000
0$
#3645000000
b1111 +
b101 ,
1$
#3650000000
0$
#3655000000
b10000 +
b110 ,
1$
#3660000000
0$
#3665000000
b10001 +
b111 ,
1$
#3670000000
0$
#3675000000
b10010 +
1$
#3680000000
0$
#3685000000
b10011 +
1$
#3690000000
0$
#3695000000
b10100 +
1$
#3700000000
0!
0(
b0 ,
1"
b1111 #
b1111 *
b1111 .
b0 &
b0 '
b0 -
0$
#3705000000
b10101 +
1$
#3710000000
0$
#3715000000
b10110 +
1$
#3720000000
0$
#3725000000
b10111 +
1$
#3730000000
0$
#3735000000
b11000 +
1$
#3740000000
0$
#3745000000
b11001 +
1$
#3750000000
0$
#3755000000
b11010 +
1$
#3760000000
0$
#3765000000
b11011 +
1$
#3770000000
0$
#3775000000
b11100 +
1$
#3780000000
0$
#3785000000
b11101 +
1$
#3790000000
0$
#3795000000
b11110 +
1$
#3800000000
0"
b1001 #
b1001 *
b1001 .
b1000000000 &
b1000000000 '
b1000000000 -
b1001 /
0$
#3805000000
b11111 +
b1 ,
1$
#3810000000
0$
#3815000000
b100000 +
b10 ,
1$
#3820000000
0$
#3825000000
b100001 +
b11 ,
1$
#3830000000
0$
#3835000000
1!
b100010 +
1(
b100 ,
1$
#3840000000
0$
#3845000000
b100011 +
b101 ,
1$
#3850000000
0$
#3855000000
b100100 +
b110 ,
1$
#3860000000
0$
#3865000000
b100101 +
b111 ,
1$
#3870000000
0$
#3875000000
b100110 +
1$
#3880000000
0$
#3885000000
b100111 +
1$
#3890000000
0$
#3895000000
b101000 +
1$
#3900000000
0!
0(
b0 ,
1"
b1111 #
b1111 *
b1111 .
b0 &
b0 '
b0 -
0$
#3905000000
b101001 +
1$
#3910000000
0$
#3915000000
b101010 +
1$
#3920000000
0$
#3925000000
b101011 +
1$
#3930000000
0$
#3935000000
b101100 +
1$
#3940000000
0$
#3945000000
b101101 +
1$
#3950000000
0$
#3955000000
b101110 +
1$
#3960000000
0$
#3965000000
b101111 +
1$
#3970000000
0$
#3975000000
b110000 +
1$
#3980000000
0$
#3985000000
b110001 +
1$
#3990000000
0$
#3995000000
b0 +
0)
1$
#4000000000
0"
b111 #
b111 *
b111 .
b10000000 &
b10000000 '
b10000000 -
b1010 /
0$
#4005000000
b1 +
b1 ,
1$
#4010000000
0$
#4015000000
b10 +
b10 ,
1$
#4020000000
b0 ,
1"
b1111 #
b1111 *
b1111 .
b10000100 &
b10000100 '
b10000100 -
0$
#4025000000
b11 +
1$
#4030000000
0$
#4035000000
b100 +
1$
#4040000000
0$
#4045000000
b101 +
1$
