P3/nivel 1/nivel 2/Entrada de timer e controle/nivel 3/Multiplexador/mux.v
module mux(
  input wire sel,
  input wire non_recycling_counter_output,
  input wire clk_1Hz,
  output reg pgt_1Hz
);

  always @* begin
    pgt_1Hz = (sel == 0) ? non_recycling_counter_output : clk_1Hz;
  end

endmodule

P3/nivel 1/nivel 2/Entrada de timer e controle/nivel 3/Multiplexador/tb_mux.v
`timescale 1ns/1ns
`include "mux.v"

module mux_teste;

    reg sel_TB, saida_contador_TB, clk_TB;
  	wire  Q_TB;

  	mux DUT(.sel(sel_TB), .non_recycling_counter_output(saida_contador_TB), .clk_1Hz(clk_TB), .pgt_1Hz(Q_TB));

    initial
        begin

            $dumpfile("mux_teste.vcd");
            $dumpvars(0, mux_teste);

                sel_TB=1; saida_contador_TB=0; clk_TB=1;
            #5  sel_TB=0; saida_contador_TB=0; clk_TB=1;
         	  #5  sel_TB=1; saida_contador_TB=1; clk_TB=0;
          	#5  sel_TB=0; saida_contador_TB=1; clk_TB=0;
            #5  sel_TB=1; saida_contador_TB=1; clk_TB=1;
          	#5  sel_TB=0; saida_contador_TB=1; clk_TB=1;
            #5  sel_TB=1; saida_contador_TB=0; clk_TB=0;
          	#5  sel_TB=0; saida_contador_TB=0; clk_TB=0;
          
        end
endmodule

P3/nivel 1/nivel 2/Entrada de timer e controle/nivel 3/Multiplexador/mux_teste.vcd
$date
	Sun Sep 24 23:34:34 2023
$end
$version
	Icarus Verilog
$end
$timescale
	1ns
$end
$scope module mux_teste $end
$var wire 1 ! Q_TB $end
$var reg 1 " clk_TB $end
$var reg 1 # saida_contador_TB $end
$var reg 1 $ sel_TB $end
$scope module DUT $end
$var wire 1 " clk_1Hz $end
$var wire 1 # non_recycling_counter_output $end
$var wire 1 $ sel $end
$var reg 1 ! pgt_1Hz $end
$upscope $end
$upscope $end
$enddefinitions $end
$comment Show the parameter values. $end
$dumpall
$end
#0
$dumpvars
1$
0#
1"
1!
$end
#5
0!
0$
#10
0"
1#
1$
#15
1!
0$
#20
1"
1$
#25
0$
#30
0!
0"
0#
1$
#35
0$
