P3/nivel 1/nivel 2/Timer de minutos segundos/nivel 3/Contador MOD6/Contador MOD6.v
module Contador_mod6 (input wire loadn, clrn, clock, enable, input wire [3:0] data,
                        output wire tc, zero, output reg [3:0] tens);


    always@(negedge clrn)begin
        if(clrn == 0)
            tens = 0;
    end

    assign zero = (tens == 0)? 1:0;
    assign tc = enable && zero;

    always@(posedge clock) begin
        if(enable == 1)
            if(tens == 0)
                tens <= 5;
            else
                tens <= tens -1;
        else
            begin
                if(loadn == 0)
                    tens <= data;
            end
    end

endmodule

P3/nivel 1/nivel 2/Timer de minutos segundos/nivel 3/Contador MOD6/Contador_mod6_tb.v
`timescale 1ps/1ps
`include "Contador MOD6.v"

module Contador_mod6_tb();

    reg loadn, clrn, clock, enable;
    reg [3:0] data;
    wire tc, zero; 
    wire [3:0] tens;
    integer i;


    Contador_mod6 DUT(.loadn(loadn), .clrn(clrn), .clock(clock), .enable(enable), .data(data),
                        .tc(tc), .zero(zero), .tens(tens));
    
    initial begin
        $dumpfile("Contador_mod6_tb.vcd");
        $dumpvars(0, Contador_mod6_tb);

        assign loadn = 1;
        assign enable = 0; 
        assign clrn = 1;
        assign data = 4'b0100;

        #5 assign loadn = 0;

        #5 assign loadn = 1;

        #5 assign enable = 1; 
    end
  
    initial begin
    	clock = 1'b0;
  	end
		
    initial begin
    	#5 clock = ~clock;
      for(i = 0; i < 26; i = i + 1)
        begin
          #5 clock = ~clock;
        end
    end

endmodule

P3/nivel 1/nivel 2/Timer de minutos segundos/nivel 3/Contador MOD6/Contador_mod6_tb.vcd
$date
	Sat Sep 23 22:10:28 2023
$end
$version
	Icarus Verilog
$end
$timescale
	1ps
$end
$scope module Contador_mod6_tb $end
$var wire 1 ! zero $end
$var wire 4 " tens [3:0] $end
$var wire 1 # tc $end
$var reg 1 $ clock $end
$var reg 1 % clrn $end
$var reg 4 & data [3:0] $end
$var reg 1 ' enable $end
$var reg 1 ( loadn $end
$var integer 32 ) i [31:0] $end
$scope module DUT $end
$var wire 1 $ clock $end
$var wire 1 % clrn $end
$var wire 4 * data [3:0] $end
$var wire 1 ' enable $end
$var wire 1 ( loadn $end
$var wire 1 # tc $end
$var wire 1 ! zero $end
$var reg 4 + tens [3:0] $end
$upscope $end
$upscope $end
$enddefinitions $end
$comment Show the parameter values. $end
$dumpall
$end
#0
$dumpvars
bx +
b100 *
bx )
1(
0'
b100 &
1%
0$
0#
bx "
x!
$end
#5
0!
b100 "
b100 +
b0 )
1$
0(
#10
b1 )
0$
1(
#15
b11 "
b11 +
b10 )
1$
1'
#20
b11 )
0$
#25
b10 "
b10 +
b100 )
1$
#30
b101 )
0$
#35
b1 "
b1 +
b110 )
1$
#40
b111 )
0$
#45
1#
1!
b0 "
b0 +
b1000 )
1$
#50
b1001 )
0$
#55
0#
0!
b101 "
b101 +
b1010 )
1$
#60
b1011 )
0$
#65
b100 "
b100 +
b1100 )
1$
#70
b1101 )
0$
#75
b11 "
b11 +
b1110 )
1$
#80
b1111 )
0$
#85
b10 "
b10 +
b10000 )
1$
#90
b10001 )
0$
#95
b1 "
b1 +
b10010 )
1$
#100
b10011 )
0$
#105
1#
1!
b0 "
b0 +
b10100 )
1$
#110
b10101 )
0$
#115
0#
0!
b101 "
b101 +
b10110 )
1$
#120
b10111 )
0$
#125
b100 "
b100 +
b11000 )
1$
#130
b11001 )
0$
#135
b11 "
b11 +
b11010 )
1$
